prs/__init__.py
prs/meta.py
prs_meta-0.0.9.dist-info/LICENSE
prs_meta-0.0.9.dist-info/METADATA
prs_meta-0.0.9.dist-info/WHEEL
prs_meta-0.0.9.dist-info/top_level.txt
prs_meta-0.0.9.dist-info/RECORD
