Metadata-Version: 2.1
Name: prs-meta
Version: 0.0.9
Summary: wrapper for pyreadstat
Author: DvGils
Author-email: demian_vg@hotmail.nl
Keywords: python,pyreadstat,SPSS,.sav
Classifier: Development Status :: 1 - Planning
Classifier: Programming Language :: Python :: 3
Classifier: Operating System :: Unix
Classifier: Operating System :: MacOS :: MacOS X
Classifier: Operating System :: Microsoft :: Windows
License-File: LICENSE
Requires-Dist: pyreadstat
Requires-Dist: pandas
